README.md
setup.py
djangoiscan.egg-info/PKG-INFO
djangoiscan.egg-info/SOURCES.txt
djangoiscan.egg-info/dependency_links.txt
djangoiscan.egg-info/not-zip-safe
djangoiscan.egg-info/requires.txt
djangoiscan.egg-info/top_level.txt
iscan/__init__.py
iscan/admin.py
iscan/api.py
iscan/apps.py
iscan/forms.py
iscan/models.py
iscan/serializers.py
iscan/tasks.py
iscan/urls.py
iscan/utils.py
iscan/views.py
iscan/annotator/__init__.py
iscan/annotator/admin.py
iscan/annotator/api.py
iscan/annotator/apps.py
iscan/annotator/models.py
iscan/annotator/serializers.py
iscan/annotator/urls.py
iscan/annotator/views.py
iscan/annotator/migrations/0001_initial.py
iscan/annotator/migrations/__init__.py
iscan/intonation/__init__.py
iscan/intonation/admin.py
iscan/intonation/api.py
iscan/intonation/apps.py
iscan/intonation/forms.py
iscan/intonation/models.py
iscan/intonation/urls.py
iscan/intonation/views.py
iscan/intonation/migrations/0001_initial.py
iscan/intonation/migrations/0002_auto_20180309_1705.py
iscan/intonation/migrations/__init__.py
iscan/migrations/0001_initial.py
iscan/migrations/0002_auto_20190530_0546.py
iscan/migrations/0003_auto_20190530_0600.py
iscan/migrations/0004_auto_20190604_1648.py
iscan/migrations/__init__.py
iscan/templatetags/__init__.py
iscan/templatetags/extra_tags.py