Metadata-Version: 2.1
Name: djangoiscan
Version: 0.2.0
Summary: Integrated Speech Corpus Analysis.
Home-page: UNKNOWN
Author: Michael McAuliffe
Author-email: michael.mcauliffe@mail.mcgill.ca
License: MIT
Platform: UNKNOWN
Classifier: Development Status :: 3 - Alpha
Classifier: Environment :: Web Environment
Classifier: Framework :: Django
Classifier: Framework :: Django :: 2.0
Classifier: Framework :: Django :: 2.1
Classifier: Intended Audience :: Developers
Classifier: License :: OSI Approved :: MIT License
Classifier: Operating System :: OS Independent
Classifier: Programming Language :: Python
Classifier: Programming Language :: Python :: 3
Classifier: Programming Language :: Python :: 3.4
Classifier: Programming Language :: Python :: 3.5
Classifier: Programming Language :: Python :: 3.6
Classifier: Topic :: Internet :: WWW/HTTP
Classifier: Topic :: Multimedia :: Sound/Audio :: Speech
Requires-Python: >=3.4
Provides-Extra: testing
